nuyidao/__init__.py
nuyidao/font/Roboto-Medium.ttf
nuyidao/svg/__init__.py
nuyidao-0.0.7.data/data/font/Roboto-Medium.ttf
nuyidao-0.0.7.dist-info/METADATA
nuyidao-0.0.7.dist-info/WHEEL
nuyidao-0.0.7.dist-info/top_level.txt
nuyidao-0.0.7.dist-info/RECORD
